yowasp_nextpnr_gowin/__init__.py
yowasp_nextpnr_gowin/nextpnr-gowin.wasm
yowasp_nextpnr_gowin/share/gowin/chipdb-GW1N-1.bin
yowasp_nextpnr_gowin/share/gowin/chipdb-GW1N-4.bin
yowasp_nextpnr_gowin/share/gowin/chipdb-GW1N-9.bin
yowasp_nextpnr_gowin/share/gowin/chipdb-GW1N-9C.bin
yowasp_nextpnr_gowin/share/gowin/chipdb-GW1NS-2.bin
yowasp_nextpnr_gowin/share/gowin/chipdb-GW1NS-4.bin
yowasp_nextpnr_gowin/share/gowin/chipdb-GW1NZ-1.bin
yowasp_nextpnr_gowin/share/gowin/chipdb-GW2A-18.bin
yowasp_nextpnr_gowin-0.7.0.0.post519.dist-info/METADATA
yowasp_nextpnr_gowin-0.7.0.0.post519.dist-info/WHEEL
yowasp_nextpnr_gowin-0.7.0.0.post519.dist-info/entry_points.txt
yowasp_nextpnr_gowin-0.7.0.0.post519.dist-info/top_level.txt
yowasp_nextpnr_gowin-0.7.0.0.post519.dist-info/RECORD
