Metadata-Version: 2.1
Name: yowasp-nextpnr-gowin
Version: 0.7.0.0.post519
Summary: nextpnr-gowin FPGA place and route tool
Author-email: Catherine <whitequark@whitequark.org>
License: ISC
Project-URL: Homepage, https://yowasp.org/
Project-URL: Source Code, https://github.com/YoWASP/nextpnr
Project-URL: Bug Tracker, https://github.com/YoWASP/nextpnr/issues
Classifier: License :: OSI Approved :: ISC License (ISCL)
Requires-Dist: yowasp-runtime ~=1.1
Requires-Dist: Apycula ==0.11.1
